[
    {
        "time": "Beyond time itself",
        "timelineEntries": [
            {
                "title": "The flower game",
                "description": "The Gardener and Winnower play a game across an infinite two dimensional grid of flowers",
                "sources": [
                    {
                        "displayName": "Unveiling - The Flower Game",
                        "type": "book",
                        "link": "https://www.ishtar-collective.net/entries/the-flower-game#book-unveiling"
                    }
                ]
            }
        ]
    },
    {
        "time": "T = 0",
        "timelineEntries": [
            {
                "title": "Birth of the Cosmos",
                "description": "The Gardener and Winnower enter the universe as Paracausal forces",
                "sources": [
                    {
                        "displayName": "Unveiling - T = 0",
                        "type": "book",
                        "link": "https://www.ishtar-collective.net/entries/t-0#book-unveiling"
                    }
                ]
            },
            {
                "description": "The Vex are created"
            }
        ]
    },
    {
        "time": "T = 0",
        "timelineEntries": [
            {
                "title": "Birth of the Cosmos",
                "description": "The Gardener and Winnower enter the universe as Paracausal forces",
                "sources": [
                    {
                        "displayName": "Unveiling - T = 0",
                        "type": "book",
                        "link": "https://www.ishtar-collective.net/entries/t-0#book-unveiling"
                    }
                ]
            },
            {
                "description": "The Vex are created"
            }
        ]
    }
]
